kyakx/__init__.py
kyakx/cli.py
kyakx/core/__init__.py
kyakx/core/banner.py
kyakx/core/dependency_checker.py
kyakx/core/encoding.py
kyakx/core/exploits.py
kyakx/core/listener.py
kyakx/core/loader.py
kyakx/core/main_menu.py
kyakx/core/shell_generator.py
kyakx/core/ssh_menu.py
kyakx/core/ssh_tools.py
kyakx/core/web_tools.py
kyakx-1.1.1.dist-info/licenses/LICENSE
kyakx-1.1.1.dist-info/METADATA
kyakx-1.1.1.dist-info/WHEEL
kyakx-1.1.1.dist-info/entry_points.txt
kyakx-1.1.1.dist-info/top_level.txt
kyakx-1.1.1.dist-info/RECORD
