Metadata-Version: 2.4
Name: kyakx
Version: 1.1.1
Summary: A powerful web exploitation toolkit
Home-page: https://github.com/kyakei/kyakx
Author: kyakei
Author-email: codtool911@gmail.com
Classifier: Programming Language :: Python :: 3
Classifier: License :: OSI Approved :: MIT License
Classifier: Operating System :: OS Independent
Requires-Python: >=3.7
License-File: LICENSE
Requires-Dist: colorama
Requires-Dist: requests
Requires-Dist: paramiko
Dynamic: author
Dynamic: author-email
Dynamic: classifier
Dynamic: description
Dynamic: description-content-type
Dynamic: home-page
Dynamic: license-file
Dynamic: requires-dist
Dynamic: requires-python
Dynamic: summary
